{
  "name": "InputDataset-countries",
  "properties": {
    "structure": [
      {
        "name": "NodeId",
        "type": "Int16"
      },
      {
        "name": "ParentId",
        "type": "Int16"
      },
      {
        "name": "Name",
        "type": "String"
      },
      {
        "name": "InsertDate",
        "type": "String"
      }
    ],
    "published": false,
    "type": "AzureSqlTable",
    "linkedServiceName": "Source-DatabaseCodere",
    "typeProperties": {
      "tableName": "[dbo].[Countries]"
    },
    "availability": {
      "frequency": "Hour",
      "interval": 1
    },
    "external": true,
    "policy": {}
  },
  "$schema": "http://datafactories.schema.management.azure.com/schemas/2015-09-01/Microsoft.DataFactory.Table.json"
}